src/__init__.py
src/rym_to_mp3/SoundCloudHandler.py
src/rym_to_mp3/YouTubeHandler.py
src/rym_to_mp3/__init__.py
src/rym_to_mp3/main.py
src/rym_to_mp3/splitHandler.py
src/rym_to_mp3/splitMP3.py
src/rym_to_mp3/writeMP3.py
rym_to_mp3-0.1.6.dist-info/LICENSE
rym_to_mp3-0.1.6.dist-info/METADATA
rym_to_mp3-0.1.6.dist-info/WHEEL
rym_to_mp3-0.1.6.dist-info/entry_points.txt
rym_to_mp3-0.1.6.dist-info/top_level.txt
rym_to_mp3-0.1.6.dist-info/RECORD
