Metadata-Version: 2.1
Name: rym-to-mp3
Version: 0.1.6
Summary: Use the RYM music database and media links to download music with correct metadata.
Home-page: https://github.com/quinnmp/rym-to-mp3
Author: Quinn Pfeifer
Author-email: quinnpfeifer@icloud.com
License: Unlicense
Requires-Python: >=3.8
License-File: LICENSE
Requires-Dist: beautifulsoup4 (>=4.12.3)
Requires-Dist: mutagen (>=1.47.0)
Requires-Dist: requests (>=2.31.0)
Requires-Dist: selenium (>=4.21.0)
Requires-Dist: webdriver-manager (>=4.0.1)
Requires-Dist: yt-dlp (>=2024.4.9)
Requires-Dist: ffmpeg-python (==0.2.0)
Requires-Dist: typing-extensions
